camel_database_agent/__init__.py
camel_database_agent/cli.py
camel_database_agent/database_agent.py
camel_database_agent/database_base.py
camel_database_agent/database_prompt.py
camel_database_agent/py.typed
camel_database_agent/core/__init__.py
camel_database_agent/core/exceptions.py
camel_database_agent/core/method_lru_cache.py
camel_database_agent/database/__init__.py
camel_database_agent/database/manager.py
camel_database_agent/database/prompts.py
camel_database_agent/database/schema.py
camel_database_agent/database/dialect/__init__.py
camel_database_agent/database/dialect/dialect.py
camel_database_agent/database/dialect/dialect_mysql.py
camel_database_agent/database/dialect/dialect_postgresql.py
camel_database_agent/database/dialect/dialect_sqlite.py
camel_database_agent/datagen/__init__.py
camel_database_agent/datagen/pipeline.py
camel_database_agent/datagen/prompts.py
camel_database_agent/knowledge/__init__.py
camel_database_agent/knowledge/knowledge.py
camel_database_agent/knowledge/knowledge_qdrant.py
camel_database_agent-0.2.0.dist-info/METADATA
camel_database_agent-0.2.0.dist-info/WHEEL
camel_database_agent-0.2.0.dist-info/licenses/LICENSE
camel_database_agent-0.2.0.dist-info/RECORD
