Metadata-Version: 2.4
Name: camel-database-agent
Version: 0.2.0
Summary: An integration package connecting Database and Camel
Project-URL: Repository, https://github.com/coolbeevip/camel-database-agent
Author: Lei Zhang
License-Expression: Apache-2.0
License-File: LICENSE
Requires-Python: <3.13,>=3.10
Requires-Dist: camel-ai[all]>=0.2.40
Requires-Dist: colorama>=0.4
Requires-Dist: dotenv>=0.9
Requires-Dist: psycopg>=3.2
Requires-Dist: pymysql==1.1.1
Requires-Dist: tabulate>=0.9
